pipenv_uv/__init__.py
pipenv_uv/__main__.py
pipenv_uv/_types.py
pipenv_uv/_version.py
pipenv_uv/py.typed
hatch_autorun_pipenv_uv.pth
pipenv_uv-0.0.6.dist-info/METADATA
pipenv_uv-0.0.6.dist-info/WHEEL
pipenv_uv-0.0.6.dist-info/entry_points.txt
pipenv_uv-0.0.6.dist-info/licenses/LICENSE.txt
pipenv_uv-0.0.6.dist-info/RECORD
