Metadata-Version: 2.4
Name: pipenv-uv
Version: 0.0.6
Summary: Patch pipenv to use uv for lock and sync operations.
Project-URL: Documentation, https://github.com/FlavioAmurrioCS/pipenv-uv#readme
Project-URL: Issues, https://github.com/FlavioAmurrioCS/pipenv-uv/issues
Project-URL: Source, https://github.com/FlavioAmurrioCS/pipenv-uv
Author-email: Flavio Amurrio <25621374+FlavioAmurrioCS@users.noreply.github.com>
License-Expression: MIT
License-File: LICENSE.txt
Keywords: pipenv,uv
Classifier: Development Status :: 4 - Beta
Classifier: Programming Language :: Python
Classifier: Programming Language :: Python :: 3.10
Classifier: Programming Language :: Python :: 3.11
Classifier: Programming Language :: Python :: 3.12
Classifier: Programming Language :: Python :: 3.13
Classifier: Programming Language :: Python :: 3.14
Classifier: Programming Language :: Python :: Implementation :: CPython
Classifier: Programming Language :: Python :: Implementation :: PyPy
Requires-Python: >=3.10
Requires-Dist: pipenv>=2025.0.4
Requires-Dist: uv>=0.9.17
